{"title":"Der einfache Investment-Plan, der wirklich funktioniert","markdown":{"yaml":{"title":"Der einfache Investment-Plan, der wirklich funktioniert"},"headingText":"Warum ein Investment-Plan wichtiger ist als jede Strategie","containsRefs":false,"markdown":"\n\n\n\n\nWenn du die letzten Kapitel gelesen hast, kennst du inzwischen viele Puzzleteile: Rendite, Risiko, Diversifikation, ETFs, Faktoren, Rebalancing, Fehlerpsychologie. Doch all dieses Wissen bringt dir nur dann wirklich etwas, wenn du es **in eine feste Struktur gießen kannst, die du langfristig durchhältst**. Genau darum geht es in diesem Kapitel: um deinen persönlichen Investment-Plan. Nicht die komplizierte Wall-Street-Variante, sondern ein **klarer, alltagstauglicher und langfristig wirksamer Plan**, der für Anfänger genauso funktioniert wie für Fortgeschrittene.\n\nUnd eines kann ich dir versprechen: Egal wie chaotisch die Finanzmärkte erscheinen, wie laut die Nachrichten schreien oder wie nervös andere werden – **ein guter Investment-Plan ist dein Ruhepol**. Er ist das Gegenmittel gegen Panik, Übermut, FOMO und impulsives Handeln. Und: Er bringt dich näher an deine Ziele, ohne dass du täglich darüber nachdenken musst.\n\n![ABB. 18.1: Der persönliche Investment-Plan als Wegkarte](images/17/ABB171.png)\n\n\nBevor wir in die konkrete 6-Schritte-Regel einsteigen, lass uns kurz klären, was ein Investment-Plan eigentlich leistet – und warum er so mächtig ist.\n\nDie meisten Menschen scheitern nicht an fehlendem Wissen. Sie scheitern an:\n\n👉 fehlender Konsequenz  \n👉 emotionalen Entscheidungen  \n👉 unklaren Zielen  \n👉 fehlenden Routinen  \n👉 impulsiven Handlungen in Stresssituationen  \n\nEin Investment-Plan löst genau diese Probleme. Er sagt dir:\n\n👉 **Wann** du investierst  \n👉 **Wie viel** du investierst  \n👉 **Worin** du investierst  \n👉 **Wie du auf Krisen reagierst**  \n👉 **Wie oft du dein Portfolio überprüfst**  \n\nKurz gesagt: \n\n> Ein Plan nimmt die Emotionen aus dem Prozess.\n\nEr verwandelt ein potenziell chaotisches Thema in eine **automatisierte Gewohnheit**. Und Gewohnheiten gewinnen immer gegen Motivation.\n\n\n## Story: Der Unterschied zwischen „Plan“ und „Gefühl“ – ein Jahr an der Börse\n\nStell dir zwei Personen vor: Lea und Jonas. Beide sind 22, beide verdienen etwas Geld neben dem Studium, beide wollen „endlich richtig investieren“.\n\n**Lea** startet ohne Plan. Sie schaut Videos, liest Posts, folgt „Finfluencern“ und handelt so, wie sie es gerade für richtig hält. Mal investiert sie schnell, mal gar nicht, mal verkauft sie wieder. Sie schwankt ständig zwischen „Ich muss sofort kaufen“ und „Oh nein, besser abwarten“.\n\n**Jonas** beginnt mit genau dem gleichen Wissen – aber er schreibt einen einfachen Investment-Plan. Ein DIN-A4-Blatt. Darauf stehen:\n\n1. 200 € monatlicher Sparplan  \n2. 80 % Welt-ETF, 20 % Faktor-ETF Momentum  \n3. Einmal jährlich Rebalancing im Januar  \n4. Portfolio nur viermal pro Jahr checken  \n5. Nie aus Panik verkaufen  \n6. Im Crash weiter besparen  \n\nNach einem Jahr unterscheidet sich ihr Verhalten dramatisch:\n\n* Lea hat zigmal die Strategie gewechselt und fühlt sich nervöser als je zuvor.  \n* Jonas hat 12 Monate investiert, ohne darüber nachdenken zu müssen. Er fühlt sich ruhig – und ist stolz.  \n\nBeide hatten dieselben Marktbedingungen. Doch nur einer hat einen Plan, der ihn geschützt hat.\n\nDiese Geschichte ist nicht übertrieben – sie passiert tausendfach genauso.\n\n    👉 Disziplin schlägt Talent. Und ein Plan erzeugt Disziplin.\n\n## Die 6-Schritte-Regel: Deine persönliche Roadmap\n\nJetzt wird’s praktisch. Dieser Abschnitt ist die Essenz moderner Anlagepsychologie, wissenschaftlicher Studien, Erfahrungswerte aus der Vermögensverwaltung – und tausenden Anlegergeschichten.\n\nDas Ziel ist ein Investment-Plan, der:\n\n* leicht zu verstehen ist  \n* ohne Fachwissen funktioniert  \n* krisensicher ist  \n* langfristig Rendite bringt  \n* zu deinem Leben passt  \n\nHier kommt sie: die **6-Schritte-Regel**, die du dir ausdrucken, einrahmen oder als Smartphone-Notiz speichern kannst.\n\n\n### Schritt 1: Definiere deine Ziele klar – und ehrlich\n\nDein Plan beginnt mit dem „Warum“. Ohne ein klares Ziel wird jede Krise zum emotionalen Problem. Mit Ziel dagegen kannst du Schwankungen besser ertragen.\n\nGute Ziele sind:\n\n👉 **konkret:** „Ich möchte mit 35 ein Finanzpolster von X € haben.“  \n👉 **zeitlich:** „Ich investiere langfristig für meine Altersvorsorge.“  \n👉 **realistisch:** „Jeden Monat 150 € investieren.“  \n\nSchlechte Ziele sind:\n\n👉 „Schnell reich werden.“  \n👉 „Ich will die beste Strategie finden.“  \n👉 „Ich möchte mehr Rendite als alle anderen.“  \n\nEin Investor ohne Ziel reagiert auf Marktbewegungen wie ein Boot ohne Kompass auf hohe Wellen.\nEin Investor mit Ziel? Der weiß, wo er hinfährt – egal wie die Wellen schlagen.\n\nDeine Aufgabe: Schreibe **ein einziges Hauptziel** auf. Nicht fünf, nicht zehn. Eins.\n\n### Schritt 2: Lege deine monatliche Anlagehöhe fest\n\nMenschen überschätzen, was sie spontan leisten können, und unterschätzen, was sie **automatisch** schaffen.\n\nDie Wissenschaft ist hier eindeutig:\n\n👉 **Regelmäßige kleine Beiträge schlagen unregelmäßige große.**  \n👉 **Automatisierung führt zu besseren Ergebnissen.**  \n👉 **Wer den Sparbetrag automatisiert, hält ihn doppelt so lange durch.**  \n\nWähle also einen Betrag, den du langfristig durchhalten kannst. Viele junge Anleger starten mit 25–200 € monatlich – das reicht vollkommen.\n\nWichtig:\nDein Betrag sollte sich *nicht* wie ein Opfer anfühlen. Du musst ihn entspannt zahlen können.\n\nWenn du nicht sicher bist:\n**Wähle am Anfang einen kleineren Betrag und erhöhe später.**\n\n\n### Schritt 3: Wähle ein einfaches Basis-Portfolio\n\nIn Kapitel 12 hast du gelernt, wie simpel ein gutes Basis-Portfolio sein kann. Der Investment-Plan enthält hier:\n\n👉 deine ETF-Auswahl  \n👉 deine Gewichtung  \n👉 deinen Rebalancing-Zeitpunkt  \n👉 optional deinen Faktor-Anteil  \n\nBeispiel für Anfänger:\n\n👉 80 % MSCI World oder FTSE All-World  \n👉 20 % Emerging Markets  \n\nBeispiel für Fortgeschrittene:\n\n👉 85 % Welt-ETF  \n👉 10 % Faktor (Momentum oder Value)  \n👉 5 % Anleihen oder Cash-Komponente  \n\nDer genaue Mix ist weniger wichtig, als viele denken.\nEntscheidend ist, **dass du konsequent investierst**.\n\n\n### Schritt 4: Lege klare Regeln für turbulente Zeiten fest\n\nDieser Schritt ist der wichtigste überhaupt. Denn Crashs werden kommen. Immer. Sie gehören zum Investieren dazu wie Regen zum Wetter.\n\nDie Forschung zeigt eindeutig:\n\n> **Anleger verlieren nicht wegen Krisen Geld, sondern wegen ihrer Reaktionen darauf.**\n\nDein Plan muss diese schwächste Stelle schützen.\n\nSchreibe deshalb klare Regeln auf, zum Beispiel:\n\n👉 „Ich verkaufe niemals aus Angst.“  \n👉 „Ich investiere weiter – auch in Krisenzeiten.“  \n👉 „Ich schaue mein Depot in Crashphasen nur einmal pro Monat an.“  \n👉 „Ich orientiere mich an meinem langfristigen Ziel, nicht an kurzfristigen Nachrichten.“  \n\nWenn eine Krise kommt, wirst du emotional reagieren. Das ist normal. Doch der Plan ersetzt in diesem Moment deine Emotionen durch klare Entscheidungen.\n\n\n### Schritt 5: Definiere einen Jahresrhythmus\n\nEin Investment-Plan ist kein starres Dokument. Er lebt. Doch er lebt strukturiert.\n\nGuter Rhythmus:\n\n👉 **Monatlich:** Automatischer Sparplan  \n👉 **Quartalsweise:** Kurzer Depotcheck  \n👉 **Jährlich:** Rebalancing + Plan-Review  \n👉 **Alle 3–5 Jahre:** Größerer Abgleich deiner Lebensziele  \n\nDas ist alles. Kein tägliches Schauen, kein stundenlanges Analysieren.\n\nDas Ziel:\n\n> **Reduziere die Zeit, die du mit Investieren verbringst – nicht erhöhe sie.**\n\nEin häufiger Fehler: Anleger denken, „mehr Arbeit“ bedeute „bessere Ergebnisse“. In Wahrheit ist das Gegenteil der Fall. Weniger Handeln = mehr Erfolg.\n\n### Schritt 6: Schreibe deinen Plan auf – und mach ihn verbindlich\n\nDas ist der wichtigste Satz dieses Kapitels:\n\n> **Ein Plan, der nicht schriftlich festgehalten ist, ist kein Plan, sondern eine Idee.**\n\nDu brauchst ein Dokument:\nEin Blatt Papier, eine Notiz, eine kleine PDF – völlig egal.\n\nDort stehen:\n\n👉 deine Ziele  \n👉 dein Sparbetrag  \n👉 deine Portfolio-Zusammensetzung  \n👉 deine Regeln für Krisen  \n👉 dein Jahresrhythmus  \n\nOptional kannst du hinzufügen:\n\n👉 wann du dein Depot anschaust  \n👉 welche Nachrichten du ignorierst  \n👉 welche Fehler du vermeiden willst  \n\nManche machen es formell:\nSie unterschreiben ihren Investment-Plan.\n\nAndere hängen ihn an die Wand.\n\nWichtig ist:\n\n> **Er ist sichtbar und griffbereit, wenn du ihn brauchst.**\n\n## Warum dieser Plan funktioniert – wissenschaftliche Basis\n\nDieser 6-Schritte-Plan baut auf Erkenntnissen aus:\n\n* Verhaltensökonomie (Kahneman, Thaler)  \n* Portfoliotheorie  \n* Habit-Forschung  \n* Studien über langfristiges Anlegerverhalten  \n* empirischen Daten zu Sparplänen  \n* den bekannten Biases wie Overconfidence oder Loss Aversion  \n\nDie Essenz all dieser Erkenntnisse lautet:\n\n* Menschen überschätzen ihre Fähigkeit, rational zu bleiben.  \n* Märkte schwanken stärker als das eigene Nervensystem.  \n* Automatisierung schützt vor impulsiven Fehlern.  \n* Einfache Strategien schlagen komplizierte in der Realität.  \n* Kontinuität ist wichtiger als Perfektion.  \n\nDeshalb funktioniert ein klarer, einfacher, schriftlicher Plan.\n\nImmer.\nFür jeden.\nIn jedem Marktumfeld.\n\n## Wie sich ein guter Plan im Alltag anfühlt\n\nEin guter Investment-Plan:\n\n* befreit dich vom ständigen Nachdenken  \n* reduziert Stress  \n* gibt dir Orientierung  \n* verhindert Panik  \n* sorgt für Routine  \n* macht Investieren unsichtbar und leicht  \n* hält dich langfristig auf Kurs  \n\nNach einigen Monaten merkst du:\nDu „investierst“ gar nicht mehr – du **bist** ein Investor.\n\nEs wird so normal wie Zähneputzen.\n\n\n\nIm ersten Teil dieses Kapitels hast du die sechs Schritte kennengelernt, die deinen Investment-Plan zu einem echten Begleiter machen – nicht nur auf dem Papier, sondern in deinem Alltag. Jetzt geht es darum, das Ganze praktisch umzusetzen. Du bekommst nachfolgend eine konkrete Vorlage, typische Stolpersteine, Anti-Stress-Regeln und die gewohnten Abschlussrubriken, die dir helfen, das Gelernte zu verinnerlichen.\n\n![ABB. 18.2: Das Zusammenspiel der drei Bausteine – Ziele, Strategie, Umsetzung](images/17/ABB172.png)\n\n\n## Die Investment-Plan-Vorlage: Dein persönlicher 1-Seiten-Plan\n\nViele Anleger scheitern daran, dass sie ihre Regeln zu kompliziert formulieren oder auf zehn Seiten ausarbeiten wollen. Doch Studien zeigen: **Je kürzer der Plan, desto eher wird er umgesetzt.**\n\nDeshalb bekommst du jetzt die **1-Seiten-Vorlage**, die du exakt so übernehmen oder nach deinen Bedürfnissen anpassen kannst. Druck sie aus, notiere deine Entscheidungen – und du bist bereit.\n\n---\n\n**Meine Ziele**\n\n* *Ich investiere langfristig, um _______ zu erreichen.*  \n* *Mein Zeithorizont beträgt mindestens _______ Jahre.*  \n* *Ich möchte mir ein finanzielles Polster aufbauen für: _______.*  \n\n---\n\n**Meine monatliche Sparrate**\n\n* *Ich investiere monatlich automatisch _______ €.*  \n* *Dieser Betrag ist realistisch und verursachte keinen Stress.*  \n\n---\n\n**Meine Portfolio-Zusammensetzung**\n\n* *Basis-Portfolio:*  \n  – _______ % Welt-ETF  \n  – _______ % EM oder weitere ETFs  \n* *Optional: Faktor-Beimischung:*  \n  – _______ % Momentum / Value / Quality / Low Risk  \n\n---\n\n**Mein Rebalancing-Rhythmus**\n\n* *Ich rebalanciere einmal pro Jahr im Monat _______.*  \n* *Ich passe meine Sparrate an, falls sich mein Einkommen dauerhaft verändert.*  \n\n---\n\n**Meine Regeln für turbulente Marktphasen**\n\n* *Ich verkaufe niemals aus Angst.*  \n* *Ich führe meinen Sparplan konsequent fort – auch bei starken Schwankungen.*  \n* *Ich schaue mein Depot in Krisen maximal _______ Mal pro Monat an.*  \n* *Ich ignoriere Panikmeldungen in den Medien.*  \n\n---\n\n**Meine Überprüfungsroutine**\n\n* *Quartalscheck: kurze Sichtung, keine Änderungen außer bei gravierenden Lebensereignissen.*  \n* *Jahrescheck: Rebalancing + Zielkontrolle.*  \n* *Alle 3–5 Jahre: Anpassung der Strategie, falls meine Lebenslage es erfordert.*  \n\n---\n\nDiese Struktur ist bewusst einfach gehalten. Sie gibt dir genug Klarheit, um strukturiert zu handeln – aber nicht so viele Details, dass der Plan zu einer „Regelmaschine“ wird, die du in der Realität nie durchhältst.\n\n---\n\n## Warum viele Pläne scheitern – und wie du das verhindern kannst\n\nViele Anleger setzen sich einen Plan, halten ihn aber nicht durch. Nicht, weil sie undiszipliniert wären, sondern weil sie typische Fehler machen. Lass uns die wichtigsten Stolpersteine anschauen – und wie du sie vermeidest.\n\n---\n\n**1. Der Perfektionismus-Falle**\n\nViele Einsteiger wollen den perfekten Plan schreiben. Sie fragen sich:\n\n* Welcher ETF ist wirklich der beste?  \n* Was ist die optimale Gewichtung?  \n* Ist Momentum besser als Value?  \n* Sollte ich jeden Monat oder alle zwei Wochen investieren?  \n\nDie Wahrheit:\n**Es gibt keinen perfekten Plan. Nur einen, der zu dir passt.**\n\nEin guter Plan ist nicht perfekt – er ist stabil.\n\n**So vermeidest du die Falle:**\nBeende deinen Plan innerhalb von 48 Stunden.\nTriff Entscheidungen. Starte. Optimierung kommt später.\n\n---\n\n**2. Zu viele Regeln**\n\nManche schreiben zehn Seiten: Regeln für Börsencrashs, für Boomphasen, für politische Krisen, für einzelne Branchen.\n\nDas Problem:\nJe komplexer dein Plan, desto eher brichst du ihn.\n\nErinnerung:\n**Der Plan soll dich befreien, nicht belasten.**\n\n---\n\n**3. Der „Ich halte mich schon daran“-Irrtum**\n\nViele sagen: „Ich muss das nicht aufschreiben, ich weiß ja, was ich vorhabe.“\n\nFalsch.\n\nStudien sind eindeutig:\n**Nur schriftlich festgehaltene Regeln beeinflussen Verhalten langfristig.**\nGedanken verfliegen im Stress. Schrift bleibt.\n\n---\n\n**4. Zu hoher Sparbetrag**\n\nEin häufiger Fehler: Man startet zu ehrgeizig und merkt nach zwei Monaten, dass es doch knapp wird.\n\nBesser:\n**Klein anfangen und später erhöhen.**\n\nEin Investment-Plan, den du nicht einhalten kannst, ist wertlos.\n\n---\n\n**5. Zu häufiges Anpassen**\n\nManche ändern ihren Plan bei jeder Marktbewegung. Das Ergebnis: Chaos.\n\nErinnerung:\nDein Plan ist dein Schutzschild vor Impulsen – nicht deren Spielball.\n\nPasse ihn nur an, wenn sich **dein Leben** verändert, nicht wenn der Markt zappelt.\n\n---\n\n## Die Anti-Stress-Regeln erfolgreicher Anleger\n\nDie folgenden Regeln stammen aus Verhaltensforschung, Behavioral Finance und den Erfahrungen vieler Vermögensverwalter. Du kannst sie in deinen Plan integrieren oder separat als Erinnerung aufhängen.\n\n---\n\n**Regel 1: Vertraue dem Prozess, nicht dem Gefühl**\n\nGefühle sind kurzfristig.\nInvestieren ist langfristig.\n\nWenn du unsicher bist, vertraue deinem Plan.\n\n---\n\n**Regel 2: Realisiere, dass Crashs normal sind**\n\nEin Crash ist kein Systemfehler – er ist Bestandteil von Rendite.\n\nDu wirst mehrere Crashs erleben. Und jeder davon wird sich extrem wichtig anfühlen. Doch aus historischer Sicht waren sie nur vorübergehende Phasen.\n\n---\n\n**Regel 3: Du musst nicht jedes Jahr gewinnen**\n\nErfolgreiche Anleger akzeptieren, dass manche Jahre schlecht laufen. Der Trend über Jahrzehnte zählt.\n\n---\n\n**Regel 4: Diversifikation schützt vor Überraschungen**\n\nKein Mensch kann sagen, welcher Markt im nächsten Jahr gewinnt.\nDiversifikation schützt dich davor, falsche Wetten zu platzieren.\n\n---\n\n**Regel 5: Dein größtes Risiko ist nicht der Markt – sondern du selbst**\n\nPanik, Gier, Übermut, Verunsicherung – all das kann dir mehr schaden als jeder Crash.\n\nDein Plan ist auch dein emotionales Sicherheitsnetz.\n\n---\n\n## Wie du deinen Plan im Alltag wirklich lebst\n\nEin guter Plan bringt dir wenig, wenn du ihn nicht in Routinen verwandelst. Hier sind zwei Techniken, die wissenschaftlich bestätigt sind und sich im Alltag bewährt haben:\n\n---\n\n**1. Die „Vorausentscheidung“**\n\nEine Vorausentscheidung ist eine Regel, die bereits definiert, wie du in einer bestimmten Lage handelst.\n\nBeispiele:\n\n👉 „Wenn der Markt stark fällt, investiere ich weiter.“  \n👉 „Wenn ich Zweifel habe, warte ich 7 Tage und treffe dann erst eine Entscheidung.“  \n\nDiese Technik reduziert impulsive Fehlentscheidungen drastisch.\n\n---\n\n**2. Das „Einmal-pro-Woche-Fenster“**\n\nLege einen Tag fest, an dem du dich maximal 10 Minuten mit Finanzen beschäftigst – z. B. Sonntagabend.\n\nIn dieser Zeit darfst du:\n\n👉 dein Depot kurz ansehen  \n👉 Nachrichten aus Filtern checken  \n👉 deinen Plan durchlesen  \n\nAußerhalb dieses Zeitfensters:\n\n**Keine Finanzentscheidungen.**\n\nDas schützt dich vor impulsiven Reaktionen.\n\n---\n\n## Beispiel: So sieht ein richtiger Investment-Plan im Leben aus\n\nSagen wir, du heißt Sam, bist 26 Jahre alt und möchtest mit 150 € monatlich investieren.\n\nDein Plan könnte so aussehen:\n\n* Ziel: In 20 Jahren ein Polster von mindestens 60.000 € aufbauen  \n* Portfolio: 80 % Welt, 20 % EM  \n* Faktor-Beimischung: 10 % Momentum (optional)  \n* Rebalancing: jedes Jahr im Februar  \n* Depotcheck: alle drei Monate  \n* Krisenregeln: keine Verkäufe wegen Angst, Sparplan läuft weiter  \n* Anpassung: alle 3–5 Jahre oder wenn sich das Einkommen deutlich ändert  \n\nSo ein Plan ist nicht spektakulär.\nAber er ist belastbar. Und das macht ihn wertvoll.\n\n## Was du aus diesem Kapitel mitnehmen solltest\n\n    ► Ein Investment-Plan schützt dich besser als jede Strategie.\n    ► Automatisierung sorgt dafür, dass du langfristig durchhältst.\n    ► Ein guter Plan ist einfach, schriftlich festgehalten und realistisch.\n    ► Disziplin entsteht nicht durch Motivation, sondern durch klare Regeln.\n    ► Emotionale Entscheidungen sind der größte Feind des Investors.\n    ► Die 6-Schritte-Regel ist deine Roadmap für jahrzehntelangen Erfolg.\n    ► Ein schlechter Plan, der durchgehalten wird, ist besser als ein perfekter, der scheitert.\n\n\n## Zum Nachdenken\n\nWarum gibt es so viele Menschen, die „über Finanzen nachdenken“, aber so wenige, die wirklich investieren?\nWarum fühlen sich Crashs so dramatisch an, obwohl sie historisch gesehen fast nie langfristige Auswirkungen haben?\nUnd was würde sich in deinem Leben verändern, wenn du ab heute einen Plan hättest, der dich nicht nur durchs Investieren, sondern durch alle finanziellen Entscheidungen begleitet?\n\nVersuch einmal, dir selbst zu beantworten:\n\n> *Welche Entscheidungen würdest du in Zukunft gerne delegieren – an deinen Investment-Plan?*\n\n\n## Ausblick\n\nMit diesem Kapitel schließt du den praktischen Teil des Buches ab. Du hast jetzt alles, was du brauchst, um langfristig und selbstbewusst zu investieren: ein klares Ziel, eine funktionierende Strategie, einen persönlichen Investment-Plan und das Wissen, wie du Fehler vermeidest. Viele Leser sind an diesem Punkt bereits bestens gerüstet, um direkt zu starten – oder ihre bestehende Strategie zu verbessern.\n\nDoch vielleicht spürst du jetzt auch etwas anderes: Neugier.\nDie Lust, noch ein bisschen tiefer einzutauchen.\nDas Bedürfnis, manche Zusammenhänge technisch genauer zu verstehen.\n\nGenau dafür gibt es den **Bonus-Teil** dieses Buches.\n\nIm nächsten Kapitel erhältst du einen Einblick, wie Profis tatsächlich arbeiten – nicht hochkompliziert, sondern anschaulich, verständlich und praxisnah. Du wirst sehen, wie Python im Investmentbereich eingesetzt wird, wie ein Momentum-Backtest funktioniert und warum Datenanalysen so entscheidend sind. Alles so erklärt, dass du es auch ohne Programmierkenntnisse nachvollziehen kannst. Und wenn du tiefer einsteigen willst: Es gibt kostenlose Jupyter-Notebooks zum Mitexperimentieren auf der Seite der **Digital Leaders Academy**.\n\nDanach wartet das **Glossar** auf dich: eine einfache, klare Sammlung aller wichtigen Begriffe aus diesem Buch. Du kannst es wie ein Wörterbuch nutzen – perfekt, wenn du später noch einmal etwas nachschlagen möchtest oder dir auf Social Media ein Finanzbegriff begegnet, den du nicht einordnen kannst.\n\nKurz gesagt:\nDu hast die Reise des „smarter Investierens“ erfolgreich gemeistert.\nJetzt liegt der Bonus-Weg vor dir – freiwillig, spannend und voller Aha-Momente.\n\nWenn du bereit bist: Lass uns eintauchen.\n\n\n","srcMarkdownNoYaml":"\n\n\n\n\nWenn du die letzten Kapitel gelesen hast, kennst du inzwischen viele Puzzleteile: Rendite, Risiko, Diversifikation, ETFs, Faktoren, Rebalancing, Fehlerpsychologie. Doch all dieses Wissen bringt dir nur dann wirklich etwas, wenn du es **in eine feste Struktur gießen kannst, die du langfristig durchhältst**. Genau darum geht es in diesem Kapitel: um deinen persönlichen Investment-Plan. Nicht die komplizierte Wall-Street-Variante, sondern ein **klarer, alltagstauglicher und langfristig wirksamer Plan**, der für Anfänger genauso funktioniert wie für Fortgeschrittene.\n\nUnd eines kann ich dir versprechen: Egal wie chaotisch die Finanzmärkte erscheinen, wie laut die Nachrichten schreien oder wie nervös andere werden – **ein guter Investment-Plan ist dein Ruhepol**. Er ist das Gegenmittel gegen Panik, Übermut, FOMO und impulsives Handeln. Und: Er bringt dich näher an deine Ziele, ohne dass du täglich darüber nachdenken musst.\n\n![ABB. 18.1: Der persönliche Investment-Plan als Wegkarte](images/17/ABB171.png)\n\n## Warum ein Investment-Plan wichtiger ist als jede Strategie\n\nBevor wir in die konkrete 6-Schritte-Regel einsteigen, lass uns kurz klären, was ein Investment-Plan eigentlich leistet – und warum er so mächtig ist.\n\nDie meisten Menschen scheitern nicht an fehlendem Wissen. Sie scheitern an:\n\n👉 fehlender Konsequenz  \n👉 emotionalen Entscheidungen  \n👉 unklaren Zielen  \n👉 fehlenden Routinen  \n👉 impulsiven Handlungen in Stresssituationen  \n\nEin Investment-Plan löst genau diese Probleme. Er sagt dir:\n\n👉 **Wann** du investierst  \n👉 **Wie viel** du investierst  \n👉 **Worin** du investierst  \n👉 **Wie du auf Krisen reagierst**  \n👉 **Wie oft du dein Portfolio überprüfst**  \n\nKurz gesagt: \n\n> Ein Plan nimmt die Emotionen aus dem Prozess.\n\nEr verwandelt ein potenziell chaotisches Thema in eine **automatisierte Gewohnheit**. Und Gewohnheiten gewinnen immer gegen Motivation.\n\n\n## Story: Der Unterschied zwischen „Plan“ und „Gefühl“ – ein Jahr an der Börse\n\nStell dir zwei Personen vor: Lea und Jonas. Beide sind 22, beide verdienen etwas Geld neben dem Studium, beide wollen „endlich richtig investieren“.\n\n**Lea** startet ohne Plan. Sie schaut Videos, liest Posts, folgt „Finfluencern“ und handelt so, wie sie es gerade für richtig hält. Mal investiert sie schnell, mal gar nicht, mal verkauft sie wieder. Sie schwankt ständig zwischen „Ich muss sofort kaufen“ und „Oh nein, besser abwarten“.\n\n**Jonas** beginnt mit genau dem gleichen Wissen – aber er schreibt einen einfachen Investment-Plan. Ein DIN-A4-Blatt. Darauf stehen:\n\n1. 200 € monatlicher Sparplan  \n2. 80 % Welt-ETF, 20 % Faktor-ETF Momentum  \n3. Einmal jährlich Rebalancing im Januar  \n4. Portfolio nur viermal pro Jahr checken  \n5. Nie aus Panik verkaufen  \n6. Im Crash weiter besparen  \n\nNach einem Jahr unterscheidet sich ihr Verhalten dramatisch:\n\n* Lea hat zigmal die Strategie gewechselt und fühlt sich nervöser als je zuvor.  \n* Jonas hat 12 Monate investiert, ohne darüber nachdenken zu müssen. Er fühlt sich ruhig – und ist stolz.  \n\nBeide hatten dieselben Marktbedingungen. Doch nur einer hat einen Plan, der ihn geschützt hat.\n\nDiese Geschichte ist nicht übertrieben – sie passiert tausendfach genauso.\n\n    👉 Disziplin schlägt Talent. Und ein Plan erzeugt Disziplin.\n\n## Die 6-Schritte-Regel: Deine persönliche Roadmap\n\nJetzt wird’s praktisch. Dieser Abschnitt ist die Essenz moderner Anlagepsychologie, wissenschaftlicher Studien, Erfahrungswerte aus der Vermögensverwaltung – und tausenden Anlegergeschichten.\n\nDas Ziel ist ein Investment-Plan, der:\n\n* leicht zu verstehen ist  \n* ohne Fachwissen funktioniert  \n* krisensicher ist  \n* langfristig Rendite bringt  \n* zu deinem Leben passt  \n\nHier kommt sie: die **6-Schritte-Regel**, die du dir ausdrucken, einrahmen oder als Smartphone-Notiz speichern kannst.\n\n\n### Schritt 1: Definiere deine Ziele klar – und ehrlich\n\nDein Plan beginnt mit dem „Warum“. Ohne ein klares Ziel wird jede Krise zum emotionalen Problem. Mit Ziel dagegen kannst du Schwankungen besser ertragen.\n\nGute Ziele sind:\n\n👉 **konkret:** „Ich möchte mit 35 ein Finanzpolster von X € haben.“  \n👉 **zeitlich:** „Ich investiere langfristig für meine Altersvorsorge.“  \n👉 **realistisch:** „Jeden Monat 150 € investieren.“  \n\nSchlechte Ziele sind:\n\n👉 „Schnell reich werden.“  \n👉 „Ich will die beste Strategie finden.“  \n👉 „Ich möchte mehr Rendite als alle anderen.“  \n\nEin Investor ohne Ziel reagiert auf Marktbewegungen wie ein Boot ohne Kompass auf hohe Wellen.\nEin Investor mit Ziel? Der weiß, wo er hinfährt – egal wie die Wellen schlagen.\n\nDeine Aufgabe: Schreibe **ein einziges Hauptziel** auf. Nicht fünf, nicht zehn. Eins.\n\n### Schritt 2: Lege deine monatliche Anlagehöhe fest\n\nMenschen überschätzen, was sie spontan leisten können, und unterschätzen, was sie **automatisch** schaffen.\n\nDie Wissenschaft ist hier eindeutig:\n\n👉 **Regelmäßige kleine Beiträge schlagen unregelmäßige große.**  \n👉 **Automatisierung führt zu besseren Ergebnissen.**  \n👉 **Wer den Sparbetrag automatisiert, hält ihn doppelt so lange durch.**  \n\nWähle also einen Betrag, den du langfristig durchhalten kannst. Viele junge Anleger starten mit 25–200 € monatlich – das reicht vollkommen.\n\nWichtig:\nDein Betrag sollte sich *nicht* wie ein Opfer anfühlen. Du musst ihn entspannt zahlen können.\n\nWenn du nicht sicher bist:\n**Wähle am Anfang einen kleineren Betrag und erhöhe später.**\n\n\n### Schritt 3: Wähle ein einfaches Basis-Portfolio\n\nIn Kapitel 12 hast du gelernt, wie simpel ein gutes Basis-Portfolio sein kann. Der Investment-Plan enthält hier:\n\n👉 deine ETF-Auswahl  \n👉 deine Gewichtung  \n👉 deinen Rebalancing-Zeitpunkt  \n👉 optional deinen Faktor-Anteil  \n\nBeispiel für Anfänger:\n\n👉 80 % MSCI World oder FTSE All-World  \n👉 20 % Emerging Markets  \n\nBeispiel für Fortgeschrittene:\n\n👉 85 % Welt-ETF  \n👉 10 % Faktor (Momentum oder Value)  \n👉 5 % Anleihen oder Cash-Komponente  \n\nDer genaue Mix ist weniger wichtig, als viele denken.\nEntscheidend ist, **dass du konsequent investierst**.\n\n\n### Schritt 4: Lege klare Regeln für turbulente Zeiten fest\n\nDieser Schritt ist der wichtigste überhaupt. Denn Crashs werden kommen. Immer. Sie gehören zum Investieren dazu wie Regen zum Wetter.\n\nDie Forschung zeigt eindeutig:\n\n> **Anleger verlieren nicht wegen Krisen Geld, sondern wegen ihrer Reaktionen darauf.**\n\nDein Plan muss diese schwächste Stelle schützen.\n\nSchreibe deshalb klare Regeln auf, zum Beispiel:\n\n👉 „Ich verkaufe niemals aus Angst.“  \n👉 „Ich investiere weiter – auch in Krisenzeiten.“  \n👉 „Ich schaue mein Depot in Crashphasen nur einmal pro Monat an.“  \n👉 „Ich orientiere mich an meinem langfristigen Ziel, nicht an kurzfristigen Nachrichten.“  \n\nWenn eine Krise kommt, wirst du emotional reagieren. Das ist normal. Doch der Plan ersetzt in diesem Moment deine Emotionen durch klare Entscheidungen.\n\n\n### Schritt 5: Definiere einen Jahresrhythmus\n\nEin Investment-Plan ist kein starres Dokument. Er lebt. Doch er lebt strukturiert.\n\nGuter Rhythmus:\n\n👉 **Monatlich:** Automatischer Sparplan  \n👉 **Quartalsweise:** Kurzer Depotcheck  \n👉 **Jährlich:** Rebalancing + Plan-Review  \n👉 **Alle 3–5 Jahre:** Größerer Abgleich deiner Lebensziele  \n\nDas ist alles. Kein tägliches Schauen, kein stundenlanges Analysieren.\n\nDas Ziel:\n\n> **Reduziere die Zeit, die du mit Investieren verbringst – nicht erhöhe sie.**\n\nEin häufiger Fehler: Anleger denken, „mehr Arbeit“ bedeute „bessere Ergebnisse“. In Wahrheit ist das Gegenteil der Fall. Weniger Handeln = mehr Erfolg.\n\n### Schritt 6: Schreibe deinen Plan auf – und mach ihn verbindlich\n\nDas ist der wichtigste Satz dieses Kapitels:\n\n> **Ein Plan, der nicht schriftlich festgehalten ist, ist kein Plan, sondern eine Idee.**\n\nDu brauchst ein Dokument:\nEin Blatt Papier, eine Notiz, eine kleine PDF – völlig egal.\n\nDort stehen:\n\n👉 deine Ziele  \n👉 dein Sparbetrag  \n👉 deine Portfolio-Zusammensetzung  \n👉 deine Regeln für Krisen  \n👉 dein Jahresrhythmus  \n\nOptional kannst du hinzufügen:\n\n👉 wann du dein Depot anschaust  \n👉 welche Nachrichten du ignorierst  \n👉 welche Fehler du vermeiden willst  \n\nManche machen es formell:\nSie unterschreiben ihren Investment-Plan.\n\nAndere hängen ihn an die Wand.\n\nWichtig ist:\n\n> **Er ist sichtbar und griffbereit, wenn du ihn brauchst.**\n\n## Warum dieser Plan funktioniert – wissenschaftliche Basis\n\nDieser 6-Schritte-Plan baut auf Erkenntnissen aus:\n\n* Verhaltensökonomie (Kahneman, Thaler)  \n* Portfoliotheorie  \n* Habit-Forschung  \n* Studien über langfristiges Anlegerverhalten  \n* empirischen Daten zu Sparplänen  \n* den bekannten Biases wie Overconfidence oder Loss Aversion  \n\nDie Essenz all dieser Erkenntnisse lautet:\n\n* Menschen überschätzen ihre Fähigkeit, rational zu bleiben.  \n* Märkte schwanken stärker als das eigene Nervensystem.  \n* Automatisierung schützt vor impulsiven Fehlern.  \n* Einfache Strategien schlagen komplizierte in der Realität.  \n* Kontinuität ist wichtiger als Perfektion.  \n\nDeshalb funktioniert ein klarer, einfacher, schriftlicher Plan.\n\nImmer.\nFür jeden.\nIn jedem Marktumfeld.\n\n## Wie sich ein guter Plan im Alltag anfühlt\n\nEin guter Investment-Plan:\n\n* befreit dich vom ständigen Nachdenken  \n* reduziert Stress  \n* gibt dir Orientierung  \n* verhindert Panik  \n* sorgt für Routine  \n* macht Investieren unsichtbar und leicht  \n* hält dich langfristig auf Kurs  \n\nNach einigen Monaten merkst du:\nDu „investierst“ gar nicht mehr – du **bist** ein Investor.\n\nEs wird so normal wie Zähneputzen.\n\n\n\nIm ersten Teil dieses Kapitels hast du die sechs Schritte kennengelernt, die deinen Investment-Plan zu einem echten Begleiter machen – nicht nur auf dem Papier, sondern in deinem Alltag. Jetzt geht es darum, das Ganze praktisch umzusetzen. Du bekommst nachfolgend eine konkrete Vorlage, typische Stolpersteine, Anti-Stress-Regeln und die gewohnten Abschlussrubriken, die dir helfen, das Gelernte zu verinnerlichen.\n\n![ABB. 18.2: Das Zusammenspiel der drei Bausteine – Ziele, Strategie, Umsetzung](images/17/ABB172.png)\n\n\n## Die Investment-Plan-Vorlage: Dein persönlicher 1-Seiten-Plan\n\nViele Anleger scheitern daran, dass sie ihre Regeln zu kompliziert formulieren oder auf zehn Seiten ausarbeiten wollen. Doch Studien zeigen: **Je kürzer der Plan, desto eher wird er umgesetzt.**\n\nDeshalb bekommst du jetzt die **1-Seiten-Vorlage**, die du exakt so übernehmen oder nach deinen Bedürfnissen anpassen kannst. Druck sie aus, notiere deine Entscheidungen – und du bist bereit.\n\n---\n\n**Meine Ziele**\n\n* *Ich investiere langfristig, um _______ zu erreichen.*  \n* *Mein Zeithorizont beträgt mindestens _______ Jahre.*  \n* *Ich möchte mir ein finanzielles Polster aufbauen für: _______.*  \n\n---\n\n**Meine monatliche Sparrate**\n\n* *Ich investiere monatlich automatisch _______ €.*  \n* *Dieser Betrag ist realistisch und verursachte keinen Stress.*  \n\n---\n\n**Meine Portfolio-Zusammensetzung**\n\n* *Basis-Portfolio:*  \n  – _______ % Welt-ETF  \n  – _______ % EM oder weitere ETFs  \n* *Optional: Faktor-Beimischung:*  \n  – _______ % Momentum / Value / Quality / Low Risk  \n\n---\n\n**Mein Rebalancing-Rhythmus**\n\n* *Ich rebalanciere einmal pro Jahr im Monat _______.*  \n* *Ich passe meine Sparrate an, falls sich mein Einkommen dauerhaft verändert.*  \n\n---\n\n**Meine Regeln für turbulente Marktphasen**\n\n* *Ich verkaufe niemals aus Angst.*  \n* *Ich führe meinen Sparplan konsequent fort – auch bei starken Schwankungen.*  \n* *Ich schaue mein Depot in Krisen maximal _______ Mal pro Monat an.*  \n* *Ich ignoriere Panikmeldungen in den Medien.*  \n\n---\n\n**Meine Überprüfungsroutine**\n\n* *Quartalscheck: kurze Sichtung, keine Änderungen außer bei gravierenden Lebensereignissen.*  \n* *Jahrescheck: Rebalancing + Zielkontrolle.*  \n* *Alle 3–5 Jahre: Anpassung der Strategie, falls meine Lebenslage es erfordert.*  \n\n---\n\nDiese Struktur ist bewusst einfach gehalten. Sie gibt dir genug Klarheit, um strukturiert zu handeln – aber nicht so viele Details, dass der Plan zu einer „Regelmaschine“ wird, die du in der Realität nie durchhältst.\n\n---\n\n## Warum viele Pläne scheitern – und wie du das verhindern kannst\n\nViele Anleger setzen sich einen Plan, halten ihn aber nicht durch. Nicht, weil sie undiszipliniert wären, sondern weil sie typische Fehler machen. Lass uns die wichtigsten Stolpersteine anschauen – und wie du sie vermeidest.\n\n---\n\n**1. Der Perfektionismus-Falle**\n\nViele Einsteiger wollen den perfekten Plan schreiben. Sie fragen sich:\n\n* Welcher ETF ist wirklich der beste?  \n* Was ist die optimale Gewichtung?  \n* Ist Momentum besser als Value?  \n* Sollte ich jeden Monat oder alle zwei Wochen investieren?  \n\nDie Wahrheit:\n**Es gibt keinen perfekten Plan. Nur einen, der zu dir passt.**\n\nEin guter Plan ist nicht perfekt – er ist stabil.\n\n**So vermeidest du die Falle:**\nBeende deinen Plan innerhalb von 48 Stunden.\nTriff Entscheidungen. Starte. Optimierung kommt später.\n\n---\n\n**2. Zu viele Regeln**\n\nManche schreiben zehn Seiten: Regeln für Börsencrashs, für Boomphasen, für politische Krisen, für einzelne Branchen.\n\nDas Problem:\nJe komplexer dein Plan, desto eher brichst du ihn.\n\nErinnerung:\n**Der Plan soll dich befreien, nicht belasten.**\n\n---\n\n**3. Der „Ich halte mich schon daran“-Irrtum**\n\nViele sagen: „Ich muss das nicht aufschreiben, ich weiß ja, was ich vorhabe.“\n\nFalsch.\n\nStudien sind eindeutig:\n**Nur schriftlich festgehaltene Regeln beeinflussen Verhalten langfristig.**\nGedanken verfliegen im Stress. Schrift bleibt.\n\n---\n\n**4. Zu hoher Sparbetrag**\n\nEin häufiger Fehler: Man startet zu ehrgeizig und merkt nach zwei Monaten, dass es doch knapp wird.\n\nBesser:\n**Klein anfangen und später erhöhen.**\n\nEin Investment-Plan, den du nicht einhalten kannst, ist wertlos.\n\n---\n\n**5. Zu häufiges Anpassen**\n\nManche ändern ihren Plan bei jeder Marktbewegung. Das Ergebnis: Chaos.\n\nErinnerung:\nDein Plan ist dein Schutzschild vor Impulsen – nicht deren Spielball.\n\nPasse ihn nur an, wenn sich **dein Leben** verändert, nicht wenn der Markt zappelt.\n\n---\n\n## Die Anti-Stress-Regeln erfolgreicher Anleger\n\nDie folgenden Regeln stammen aus Verhaltensforschung, Behavioral Finance und den Erfahrungen vieler Vermögensverwalter. Du kannst sie in deinen Plan integrieren oder separat als Erinnerung aufhängen.\n\n---\n\n**Regel 1: Vertraue dem Prozess, nicht dem Gefühl**\n\nGefühle sind kurzfristig.\nInvestieren ist langfristig.\n\nWenn du unsicher bist, vertraue deinem Plan.\n\n---\n\n**Regel 2: Realisiere, dass Crashs normal sind**\n\nEin Crash ist kein Systemfehler – er ist Bestandteil von Rendite.\n\nDu wirst mehrere Crashs erleben. Und jeder davon wird sich extrem wichtig anfühlen. Doch aus historischer Sicht waren sie nur vorübergehende Phasen.\n\n---\n\n**Regel 3: Du musst nicht jedes Jahr gewinnen**\n\nErfolgreiche Anleger akzeptieren, dass manche Jahre schlecht laufen. Der Trend über Jahrzehnte zählt.\n\n---\n\n**Regel 4: Diversifikation schützt vor Überraschungen**\n\nKein Mensch kann sagen, welcher Markt im nächsten Jahr gewinnt.\nDiversifikation schützt dich davor, falsche Wetten zu platzieren.\n\n---\n\n**Regel 5: Dein größtes Risiko ist nicht der Markt – sondern du selbst**\n\nPanik, Gier, Übermut, Verunsicherung – all das kann dir mehr schaden als jeder Crash.\n\nDein Plan ist auch dein emotionales Sicherheitsnetz.\n\n---\n\n## Wie du deinen Plan im Alltag wirklich lebst\n\nEin guter Plan bringt dir wenig, wenn du ihn nicht in Routinen verwandelst. Hier sind zwei Techniken, die wissenschaftlich bestätigt sind und sich im Alltag bewährt haben:\n\n---\n\n**1. Die „Vorausentscheidung“**\n\nEine Vorausentscheidung ist eine Regel, die bereits definiert, wie du in einer bestimmten Lage handelst.\n\nBeispiele:\n\n👉 „Wenn der Markt stark fällt, investiere ich weiter.“  \n👉 „Wenn ich Zweifel habe, warte ich 7 Tage und treffe dann erst eine Entscheidung.“  \n\nDiese Technik reduziert impulsive Fehlentscheidungen drastisch.\n\n---\n\n**2. Das „Einmal-pro-Woche-Fenster“**\n\nLege einen Tag fest, an dem du dich maximal 10 Minuten mit Finanzen beschäftigst – z. B. Sonntagabend.\n\nIn dieser Zeit darfst du:\n\n👉 dein Depot kurz ansehen  \n👉 Nachrichten aus Filtern checken  \n👉 deinen Plan durchlesen  \n\nAußerhalb dieses Zeitfensters:\n\n**Keine Finanzentscheidungen.**\n\nDas schützt dich vor impulsiven Reaktionen.\n\n---\n\n## Beispiel: So sieht ein richtiger Investment-Plan im Leben aus\n\nSagen wir, du heißt Sam, bist 26 Jahre alt und möchtest mit 150 € monatlich investieren.\n\nDein Plan könnte so aussehen:\n\n* Ziel: In 20 Jahren ein Polster von mindestens 60.000 € aufbauen  \n* Portfolio: 80 % Welt, 20 % EM  \n* Faktor-Beimischung: 10 % Momentum (optional)  \n* Rebalancing: jedes Jahr im Februar  \n* Depotcheck: alle drei Monate  \n* Krisenregeln: keine Verkäufe wegen Angst, Sparplan läuft weiter  \n* Anpassung: alle 3–5 Jahre oder wenn sich das Einkommen deutlich ändert  \n\nSo ein Plan ist nicht spektakulär.\nAber er ist belastbar. Und das macht ihn wertvoll.\n\n## Was du aus diesem Kapitel mitnehmen solltest\n\n    ► Ein Investment-Plan schützt dich besser als jede Strategie.\n    ► Automatisierung sorgt dafür, dass du langfristig durchhältst.\n    ► Ein guter Plan ist einfach, schriftlich festgehalten und realistisch.\n    ► Disziplin entsteht nicht durch Motivation, sondern durch klare Regeln.\n    ► Emotionale Entscheidungen sind der größte Feind des Investors.\n    ► Die 6-Schritte-Regel ist deine Roadmap für jahrzehntelangen Erfolg.\n    ► Ein schlechter Plan, der durchgehalten wird, ist besser als ein perfekter, der scheitert.\n\n\n## Zum Nachdenken\n\nWarum gibt es so viele Menschen, die „über Finanzen nachdenken“, aber so wenige, die wirklich investieren?\nWarum fühlen sich Crashs so dramatisch an, obwohl sie historisch gesehen fast nie langfristige Auswirkungen haben?\nUnd was würde sich in deinem Leben verändern, wenn du ab heute einen Plan hättest, der dich nicht nur durchs Investieren, sondern durch alle finanziellen Entscheidungen begleitet?\n\nVersuch einmal, dir selbst zu beantworten:\n\n> *Welche Entscheidungen würdest du in Zukunft gerne delegieren – an deinen Investment-Plan?*\n\n\n## Ausblick\n\nMit diesem Kapitel schließt du den praktischen Teil des Buches ab. Du hast jetzt alles, was du brauchst, um langfristig und selbstbewusst zu investieren: ein klares Ziel, eine funktionierende Strategie, einen persönlichen Investment-Plan und das Wissen, wie du Fehler vermeidest. Viele Leser sind an diesem Punkt bereits bestens gerüstet, um direkt zu starten – oder ihre bestehende Strategie zu verbessern.\n\nDoch vielleicht spürst du jetzt auch etwas anderes: Neugier.\nDie Lust, noch ein bisschen tiefer einzutauchen.\nDas Bedürfnis, manche Zusammenhänge technisch genauer zu verstehen.\n\nGenau dafür gibt es den **Bonus-Teil** dieses Buches.\n\nIm nächsten Kapitel erhältst du einen Einblick, wie Profis tatsächlich arbeiten – nicht hochkompliziert, sondern anschaulich, verständlich und praxisnah. Du wirst sehen, wie Python im Investmentbereich eingesetzt wird, wie ein Momentum-Backtest funktioniert und warum Datenanalysen so entscheidend sind. Alles so erklärt, dass du es auch ohne Programmierkenntnisse nachvollziehen kannst. Und wenn du tiefer einsteigen willst: Es gibt kostenlose Jupyter-Notebooks zum Mitexperimentieren auf der Seite der **Digital Leaders Academy**.\n\nDanach wartet das **Glossar** auf dich: eine einfache, klare Sammlung aller wichtigen Begriffe aus diesem Buch. Du kannst es wie ein Wörterbuch nutzen – perfekt, wenn du später noch einmal etwas nachschlagen möchtest oder dir auf Social Media ein Finanzbegriff begegnet, den du nicht einordnen kannst.\n\nKurz gesagt:\nDu hast die Reise des „smarter Investierens“ erfolgreich gemeistert.\nJetzt liegt der Bonus-Weg vor dir – freiwillig, spannend und voller Aha-Momente.\n\nWenn du bereit bist: Lass uns eintauchen.\n\n\n"},"formats":{"html":{"identifier":{"display-name":"HTML","target-format":"html","base-format":"html"},"execute":{"fig-width":7,"fig-height":5,"fig-format":"retina","fig-dpi":96,"df-print":"default","error":false,"eval":true,"cache":null,"freeze":false,"echo":true,"output":true,"warning":true,"include":true,"keep-md":false,"keep-ipynb":false,"ipynb":null,"enabled":false,"daemon":null,"daemon-restart":false,"debug":false,"ipynb-filters":[],"ipynb-shell-interactivity":null,"plotly-connected":true,"engine":"jupyter"},"render":{"keep-tex":false,"keep-typ":false,"keep-source":false,"keep-hidden":false,"prefer-html":false,"output-divs":true,"output-ext":"html","fig-align":"default","fig-pos":null,"fig-env":null,"code-fold":true,"code-overflow":"scroll","code-link":false,"code-line-numbers":true,"code-tools":false,"tbl-colwidths":"auto","merge-includes":true,"inline-includes":false,"preserve-yaml":false,"latex-auto-mk":true,"latex-auto-install":true,"latex-clean":true,"latex-min-runs":1,"latex-max-runs":10,"latex-makeindex":"makeindex","latex-makeindex-opts":[],"latex-tlmgr-opts":[],"latex-input-paths":[],"latex-output-dir":null,"link-external-icon":false,"link-external-newwindow":true,"self-contained-math":false,"format-resources":[],"notebook-links":true},"pandoc":{"standalone":true,"wrap":"none","default-image-extension":"png","to":"html","toc":true,"toc-depth":3,"number-sections":true,"css":["styles.css"],"output-file":"kapitel17.html"},"language":{"toc-title-document":"Table of contents","toc-title-website":"On this page","related-formats-title":"Other Formats","related-notebooks-title":"Notebooks","source-notebooks-prefix":"Source","other-links-title":"Other Links","code-links-title":"Code Links","launch-dev-container-title":"Launch Dev Container","launch-binder-title":"Launch Binder","article-notebook-label":"Article Notebook","notebook-preview-download":"Download Notebook","notebook-preview-download-src":"Download Source","notebook-preview-back":"Back to Article","manuscript-meca-bundle":"MECA Bundle","section-title-abstract":"Abstract","section-title-appendices":"Appendices","section-title-footnotes":"Footnotes","section-title-references":"References","section-title-reuse":"Reuse","section-title-copyright":"Copyright","section-title-citation":"Citation","appendix-attribution-cite-as":"For attribution, please cite this work as:","appendix-attribution-bibtex":"BibTeX citation:","appendix-view-license":"View License","title-block-author-single":"Author","title-block-author-plural":"Authors","title-block-affiliation-single":"Affiliation","title-block-affiliation-plural":"Affiliations","title-block-published":"Published","title-block-modified":"Modified","title-block-keywords":"Keywords","callout-tip-title":"Tip","callout-note-title":"Note","callout-warning-title":"Warning","callout-important-title":"Important","callout-caution-title":"Caution","code-summary":"Code","code-tools-menu-caption":"Code","code-tools-show-all-code":"Show All Code","code-tools-hide-all-code":"Hide All Code","code-tools-view-source":"View Source","code-tools-source-code":"Source Code","tools-share":"Share","tools-download":"Download","code-line":"Line","code-lines":"Lines","copy-button-tooltip":"Copy to Clipboard","copy-button-tooltip-success":"Copied!","repo-action-links-edit":"Edit this page","repo-action-links-source":"View source","repo-action-links-issue":"Report an issue","back-to-top":"Back to top","search-no-results-text":"No results","search-matching-documents-text":"matching documents","search-copy-link-title":"Copy link to search","search-hide-matches-text":"Hide additional matches","search-more-match-text":"more match in this document","search-more-matches-text":"more matches in this document","search-clear-button-title":"Clear","search-text-placeholder":"","search-detached-cancel-button-title":"Cancel","search-submit-button-title":"Submit","search-label":"Search","toggle-section":"Toggle section","toggle-sidebar":"Toggle sidebar navigation","toggle-dark-mode":"Toggle dark mode","toggle-reader-mode":"Toggle reader mode","toggle-navigation":"Toggle navigation","crossref-fig-title":"Figure","crossref-tbl-title":"Table","crossref-lst-title":"Listing","crossref-thm-title":"Theorem","crossref-lem-title":"Lemma","crossref-cor-title":"Corollary","crossref-prp-title":"Proposition","crossref-cnj-title":"Conjecture","crossref-def-title":"Definition","crossref-exm-title":"Example","crossref-exr-title":"Exercise","crossref-ch-prefix":"Chapter","crossref-apx-prefix":"Appendix","crossref-sec-prefix":"Section","crossref-eq-prefix":"Equation","crossref-lof-title":"List of Figures","crossref-lot-title":"List of Tables","crossref-lol-title":"List of Listings","environment-proof-title":"Proof","environment-remark-title":"Remark","environment-solution-title":"Solution","listing-page-order-by":"Order By","listing-page-order-by-default":"Default","listing-page-order-by-date-asc":"Oldest","listing-page-order-by-date-desc":"Newest","listing-page-order-by-number-desc":"High to Low","listing-page-order-by-number-asc":"Low to High","listing-page-field-date":"Date","listing-page-field-title":"Title","listing-page-field-description":"Description","listing-page-field-author":"Author","listing-page-field-filename":"File Name","listing-page-field-filemodified":"Modified","listing-page-field-subtitle":"Subtitle","listing-page-field-readingtime":"Reading Time","listing-page-field-wordcount":"Word Count","listing-page-field-categories":"Categories","listing-page-minutes-compact":"{0} min","listing-page-category-all":"All","listing-page-no-matches":"No matching items","listing-page-words":"{0} words","listing-page-filter":"Filter","draft":"Draft"},"metadata":{"lang":"en","fig-responsive":true,"quarto-version":"1.8.25","theme":{"light":"flatly","dark":"darkly"},"code-copy":true,"smooth-scroll":true,"title":"Der einfache Investment-Plan, der wirklich funktioniert"},"extensions":{"book":{"multiFile":true}}}},"projectFormats":["html"]}